pytrika/__init__.py
pytrika/currentproject/__init__.py
pytrika/currentproject/project.py
pytrika/mozillabookmark/__init__.py
pytrika/mozillabookmark/bookmark.py
pytrika-0.1.9.data/scripts/cthis
pytrika-0.1.9.data/scripts/fthis
pytrika-0.1.9.dist-info/LICENSE
pytrika-0.1.9.dist-info/METADATA
pytrika-0.1.9.dist-info/WHEEL
pytrika-0.1.9.dist-info/top_level.txt
pytrika-0.1.9.dist-info/RECORD
