Metadata-Version: 2.1
Name: pytrika
Version: 0.1.9
Summary: This git-compatible module helps in organizing project specific web-url-resources. It does it by using the built-in bookmark-manager in browsers.
Home-page: https://github.com/llk23r/pytrika
Author: Rahul Acharya
Author-email: mail.acharyarahul.now@gmail.com
License: UNKNOWN
Platform: UNKNOWN
Classifier: Programming Language :: Python :: 3.6
Classifier: Operating System :: OS Independent
Requires-Dist: termcolor (>=1.1.0)
Requires-Dist: colorama
